itermae/__init__.py
itermae/tests/__init__.py
itermae/tests/test.py
itermae-0.6.0.1.data/scripts/itermae
itermae-0.6.0.1.dist-info/LICENSE
itermae-0.6.0.1.dist-info/METADATA
itermae-0.6.0.1.dist-info/WHEEL
itermae-0.6.0.1.dist-info/top_level.txt
itermae-0.6.0.1.dist-info/RECORD
