Metadata-Version: 2.1
Name: itermae
Version: 0.6.0.1
Summary: Commandline tool for parsing NGS reads by multiple fuzzy regex operations
Home-page: http://gitlab.com/darachm/itermae
Author: Darach Miller
Author-email: darachm@stanford.edu
License: BSD 2-clause
Keywords: fastq regex fuzzy amplicon parser barcode extractor extracter
Platform: UNKNOWN
Classifier: Development Status :: 3 - Alpha
Classifier: Intended Audience :: Developers
Classifier: Topic :: Scientific/Engineering :: Bio-Informatics
Classifier: Programming Language :: Python :: 3
Requires-Python: >=3.6
Requires-Dist: biopython
Requires-Dist: pyyaml
Requires-Dist: regex
